MANIFEST.in
setup.py
src/verst/__init__.py
src/verst.pants.docker.egg-info/PKG-INFO
src/verst.pants.docker.egg-info/SOURCES.txt
src/verst.pants.docker.egg-info/dependency_links.txt
src/verst.pants.docker.egg-info/entry_points.txt
src/verst.pants.docker.egg-info/namespace_packages.txt
src/verst.pants.docker.egg-info/requires.txt
src/verst.pants.docker.egg-info/top_level.txt
src/verst.pants.docker.egg-info/zip-safe
src/verst/pants/__init__.py
src/verst/pants/docker/__init__.py
src/verst/pants/docker/docker_base_task.py
src/verst/pants/docker/docker_jvm_app_bundle_task.py
src/verst/pants/docker/docker_publish.py
src/verst/pants/docker/docker_python_bundle_task.py
src/verst/pants/docker/docker_run.py
src/verst/pants/docker/register.py
src/verst/pants/docker/target.py