Metadata-Version: 1.1
Name: verst.pants.docker
Version: 1.2.0
Summary: A docker plugin for pants
Home-page: https://github.com/toddgardner/pants-plugins
Author: Todd Gardner
Author-email: todd.gardner@gmail.com
License: MIT
Platform: UNKNOWN
Classifier: Intended Audience :: Developers
Classifier: License :: OSI Approved :: MIT License
Classifier: Operating System :: MacOS :: MacOS X
Classifier: Operating System :: POSIX :: Linux
Classifier: Topic :: Software Development :: Build Tools
